{
    "run_name": "test-run",
    "max_train_samples" : 10,
    "max_eval_samples" : 10,
    "dataset_name": "nerel-bio-fix",
    "model_name_or_path": "DeepPavlov/rubert-base-cased",
    "train_file": "data/nerel-bio-fix/train.json",
    "validation_file": "data/nerel-bio-fix/dev.json",
    "test_file": "data/nerel-bio-fix/test.json",
    "entity_type_file": "entity_types.json",
    "dataset_entity_types": ["ACTIVITY", "ADMINISTRATION_ROUTE", "AGE", "ANATOMY", "CHEM", "CITY", "COUNTRY", "DATE", "DEVICE", "DISO", "DISTRICT", "EVENT", "FACILITY", "FAMILY", "FINDING", "FOOD", "GENE", "HEALTH_CARE_ACTIVITY", "INJURY_POISONING", "LABPROC", "LIVB", "LOCATION", "MEDPROC", "MENTALPROC", "MONEY", "NATIONALITY", "NUMBER", "ORDINAL", "ORGANIZATION", "PERCENT", "PERSON", "PHYS", "PRODUCT", "PROFESSION", "SCIPROC", "STATE_OR_PROVINCE", "TIME"],
    "report_to": "none",
    "max_steps" : 10,
    "eval_steps" : 10,
    "wandb_project" : "Binder-Nerel",
    "max_seq_length": 4,
    "use_span_width_embedding": true,
    "doc_stride": 0,
    "preprocessing_num_workers": 4,
    "dataloader_num_workers": 4,
    "overwrite_cache": false,
    "overwrite_output_dir": true,
    "do_train": true,
    "fp16": true,
    "gradient_checkpointing": false,
    "optim": "adamw_torch",
    "label_names": ["ner"],
    "num_train_epochs": 1,
    "per_device_train_batch_size": 4,
    "gradient_accumulation_steps": 1,
    "learning_rate": 3e-5,
    "logging_steps": 10,
    "load_best_model_at_end": true,
    "metric_for_best_model": "f1",
    "greater_is_better": true,
    "save_strategy": "steps",
    "save_steps": 100,
    "save_total_limit": 1,
    "do_eval": false,
    "evaluation_strategy": "steps",
    "eval_steps": 100,
    "do_predict": false,
    "output_dir": "./logs/nerel-bio-fix/rubert"
}