{"dataset": "nerel", "name": "AGE", "description": "AGE - это сущности, такие как год, 40-летний, 26-летний, 54-летний, 25-летний.", "description_source": "5-most Frequent Components Prompt"}
{"dataset": "nerel", "name": "AWARD", "description": "AWARD - это сущности, такие как премия, нобелевский, мир, хороший, чемпион.", "description_source": "5-most Frequent Components Prompt"}
{"dataset": "nerel", "name": "CITY", "description": "CITY - это сущности, такие как москва, московский, нью-йорк, лондон, киев.", "description_source": "5-most Frequent Components Prompt"}
{"dataset": "nerel", "name": "COUNTRY", "description": "COUNTRY - это сущности, такие как россия, сша, российский, рф, украина.", "description_source": "5-most Frequent Components Prompt"}
{"dataset": "nerel", "name": "CRIME", "description": "CRIME - это сущности, такие как убийство, мошенничество, коррупция, хищение, преступление.", "description_source": "5-most Frequent Components Prompt"}
{"dataset": "nerel", "name": "DATE", "description": "DATE - это сущности, такие как год, в, 2013, 2016, 2017.", "description_source": "5-most Frequent Components Prompt"}
{"dataset": "nerel", "name": "DISEASE", "description": "DISEASE - это сущности, такие как рак, травма, состояние, приступ, сердечный.", "description_source": "5-most Frequent Components Prompt"}
{"dataset": "nerel", "name": "DISTRICT", "description": "DISTRICT - это сущности, такие как район, округ, военный, манхеттен, северокавказский.", "description_source": "5-most Frequent Components Prompt"}
{"dataset": "nerel", "name": "EVENT", "description": "EVENT - это сущности, такие как выборы, отставка, скончаться, погибнуть, назначить.", "description_source": "5-most Frequent Components Prompt"}
{"dataset": "nerel", "name": "FACILITY", "description": "FACILITY - это сущности, такие как дом, больница, улица, памятник, собор.", "description_source": "5-most Frequent Components Prompt"}
{"dataset": "nerel", "name": "FAMILY", "description": "FAMILY - это сущности, такие как семья, брат, царнаева, королевский, романов.", "description_source": "5-most Frequent Components Prompt"}
{"dataset": "nerel", "name": "IDEOLOGY", "description": "IDEOLOGY - это сущности, такие как демократ, демократический, оппозиционный, республиканец, оппозиция.", "description_source": "5-most Frequent Components Prompt"}
{"dataset": "nerel", "name": "LANGUAGE", "description": "LANGUAGE - это сущности, такие как английский, русский, арабский, немецкий, французский.", "description_source": "5-most Frequent Components Prompt"}
{"dataset": "nerel", "name": "LAW", "description": "LAW - это сущности, такие как ук, рф, закон, ., о.", "description_source": "5-most Frequent Components Prompt"}
{"dataset": "nerel", "name": "LOCATION", "description": "LOCATION - это сущности, такие как европа, европейский, море, западный, африка.", "description_source": "5-most Frequent Components Prompt"}
{"dataset": "nerel", "name": "MONEY", "description": "MONEY - это сущности, такие как доллар, млн, рубль, миллион, сша.", "description_source": "5-most Frequent Components Prompt"}
{"dataset": "nerel", "name": "NATIONALITY", "description": "NATIONALITY - это сущности, такие как американский, россиянин, гражданин, русский, американец.", "description_source": "5-most Frequent Components Prompt"}
{"dataset": "nerel", "name": "NUMBER", "description": "NUMBER - это сущности, такие как два, тысяча, четыре, один, около.", "description_source": "5-most Frequent Components Prompt"}
{"dataset": "nerel", "name": "ORDINAL", "description": "ORDINAL - это сущности, такие как первый, второй, третий, ii, четвёртый.", "description_source": "5-most Frequent Components Prompt"}
{"dataset": "nerel", "name": "ORGANIZATION", "description": "ORGANIZATION - это сущности, такие как правительство, россия, полиция, совет, суд.", "description_source": "5-most Frequent Components Prompt"}
{"dataset": "nerel", "name": "PERCENT", "description": "PERCENT - это сущности, такие как %, процент, 1, 50, 90.", "description_source": "5-most Frequent Components Prompt"}
{"dataset": "nerel", "name": "PERSON", "description": "PERSON - это сущности, такие как владимир, путин, сергей, александр, дмитрий.", "description_source": "5-most Frequent Components Prompt"}
{"dataset": "nerel", "name": "PENALTY", "description": "PENALTY - это сущности, такие как год, свобода, тюрьма, лишение, заключение.", "description_source": "5-most Frequent Components Prompt"}
{"dataset": "nerel", "name": "PRODUCT", "description": "PRODUCT - это сущности, такие как интернет, facebook, твиттер, twitter, youtube.", "description_source": "5-most Frequent Components Prompt"}
{"dataset": "nerel", "name": "PROFESSION", "description": "PROFESSION - это сущности, такие как президент, глава, министр, премьер-министр, директор.", "description_source": "5-most Frequent Components Prompt"}
{"dataset": "nerel", "name": "RELIGION", "description": "RELIGION - это сущности, такие как мусульманин, исламский, православный, ислам, мусульманский.", "description_source": "5-most Frequent Components Prompt"}
{"dataset": "nerel", "name": "STATE_OR_PROVINCE", "description": "STATE_OR_PROVINCE - это сущности, такие как область, калифорния, край, массачусетс, техас.", "description_source": "5-most Frequent Components Prompt"}
{"dataset": "nerel", "name": "TIME", "description": "TIME - это сущности, такие как час, минута, год, вечером, утром.", "description_source": "5-most Frequent Components Prompt"}
{"dataset": "nerel", "name": "WORK_OF_ART", "description": "WORK_OF_ART - это сущности, такие как the, ,, ., !, день.", "description_source": "5-most Frequent Components Prompt"}
